pdq-0.1.0a0.dist-info/METADATA
pdq-0.1.0a0.dist-info/WHEEL
pdq-0.1.0a0.dist-info/licenses/LICENSE
pdq/__init__.py
pdq/pdq.cpython-313-darwin.so
pdq-0.1.0a0.dist-info/RECORD
