Metadata-Version: 2.4
Name: pdq
Version: 0.1.0a0
License-File: LICENSE
Summary: Coming soon! Pretty darn quick Parquet side index using FST
License: MIT
Requires-Python: >=3.9
Project-URL: Source Code, https://github.com/erichutchins/pdq
